setup.py
xdata/__init__.py
xdata/exceptions.py
xdata/schema.py
xdata/types.py
xdata.egg-info/PKG-INFO
xdata.egg-info/SOURCES.txt
xdata.egg-info/dependency_links.txt
xdata.egg-info/top_level.txt