Metadata-Version: 1.1
Name: xdata
Version: 0.0.3
Summary: Simple data validation library
Home-page: https://github.com/gaojiuli/xdata
Author: gaojiuli
Author-email: gaojiuli@gmail.com
License: MIT
Keywords: schema json validation
Platform: any
Classifier: Development Status :: 3 - Alpha
Classifier: Topic :: Utilities
Classifier: Programming Language :: Python :: 3.5
Classifier: Programming Language :: Python :: 3.6
Classifier: Programming Language :: Python :: Implementation :: PyPy
Classifier: License :: OSI Approved :: MIT License
